CHANGES.txt
LICENSE.txt
README.txt
setup.py
inquant/__init__.py
inquant.recipe.textfile.egg-info/PKG-INFO
inquant.recipe.textfile.egg-info/SOURCES.txt
inquant.recipe.textfile.egg-info/dependency_links.txt
inquant.recipe.textfile.egg-info/entry_points.txt
inquant.recipe.textfile.egg-info/namespace_packages.txt
inquant.recipe.textfile.egg-info/not-zip-safe
inquant.recipe.textfile.egg-info/requires.txt
inquant.recipe.textfile.egg-info/top_level.txt
inquant/recipe/__init__.py
inquant/recipe/textfile/__init__.py