Metadata-Version: 1.0
Name: inquant.recipe.textfile
Version: 0.2.3
Summary: ZC Buildout recipe for creating text files out of templates.
Home-page: https://svn.inquant.de/inquant/develop/plone/recipes/inquant.recipe.textfile
Author: Stefan Eletzhofer
Author-email: stefan.eletzhofer@inquant.de
License: LGPL
Keywords: buildout recipe setup template
Platform: UNKNOWN
Classifier: Framework :: Buildout
Classifier: Programming Language :: Python
Classifier: Topic :: Software Development :: Libraries :: Python Modules
